Workbook

Sheet Model
A1: REL 成本模型 · 28gsm vs 40gsm 传统 REL
A2: 版本 2026-10-23 ｜ 依据恒碳 PTT/PET 成本交底（千吨级 20,000–21,000 元/t）｜ 蓝色单元格可改，其余自动重算
A4: ① 输入参数（蓝色 = 可改）
A5: 参数 | B5: 数值 | C5: 单位 | D5: 说明 / 来源
A6: PTT/PET S/S 纤维价 | B6: 20500 | C6: 元/t | D6: 恒碳千吨级 20,000–21,000，取中值
A7: 设计克重 | B7: 28.8 | C7: gsm | D7: 图纸 / 标称克重
A8: 实际成网克重 | B8: 33 | C8: gsm | D8: 回缩后实测（会议：28-29 → 33）
A9: PTT 添加比例 | B9: 0.22 | C9: % | D9: 会议确认，合理区间 10%–30%
A10: ES CoPET/PET 2D 单价 | B10: 11600 | C10: 元/t | D10: 卫材级复合短纤
A11: ES CoPET/PET 3D 单价 | B11: 11600 | C11: 元/t | D11: 同上
A12: 偏心中空 ES 单价 | B12: 13500 | C12: 元/t | D12: 待核实（若 12,000 全成本再降 0.0043）
A13: PVA 6D 单价 | B13: 20000 | C13: 元/t | D13: 皖维高新
A14: 加工费 | B14: 4500 | C14: 元/t | D14: ATB 热风粘合 + 分切
A15: 单片面积 | B15: 0.038 | C15: m² | D15: 约 100×380mm，可按实际改
A16: 年产量 | B16: 1 | C16: 亿片 | D16: 用于年度金额测算
A17: 传统 40gsm 基准全成本 | B17: 0.5775 | C17: 元/m² | D17: 4 条竞品基线均值（见 Compare 页）
A19: ② 配方与吨成本（非 PTT 组分按 34:8:30:6 归一化）
A20: 纤维 | B20: 占比 | C20: 单价 元/t | D20: 摊入 元/t
A21: ES CoPET/PET 2D | B21: =(1-$B$9)*34/78 | C21: =$B$10 | D21: =B21*C21
A22: ES CoPET/PET 3D | B22: =(1-$B$9)*8/78 | C22: =$B$11 | D22: =B22*C22
A23: 偏心中空 ES | B23: =(1-$B$9)*30/78 | C23: =$B$12 | D23: =B23*C23
A24: PVA 水不溶 6D | B24: =(1-$B$9)*6/78 | C24: =$B$13 | D24: =B24*C24
A25: PTT/PET S/S 7D | B25: =$B$9 | C25: =$B$6 | D25: =B25*C25
A26: 配方成本合计 | B26: =SUM(B21:B25) | D26: =SUM(D21:D25)
A28: ③ 单位成本测算
A29: 项目 | B29: 设计克重 | C29: 实际成网 | D29: 单位
A30: 克重 | B30: =$B$7 | C30: =$B$8 | D30: gsm
A31: 纤维成本 / m² | B31: =($D$26*B30)/1000000 | C31: =($D$26*C30)/1000000 | D31: 元/m²
A32: 加工成本 / m² | B32: =($B$14*B30)/1000000 | C32: =($B$14*C30)/1000000 | D32: 元/m²
A33: 全成本 / m² | B33: =B31+B32 | C33: =C31+C32 | D33: 元/m²
A34: 元 / 片 | B34: =B33*$B$15 | C34: =C33*$B$15 | D34: 元/片
A35: vs 传统 40gsm | B35: =B33/$B$17-1 | C35: =C33/$B$17-1 | D35: %
A36: 年度总成本 | B36: =B34*$B$16*10000 | C36: =C34*$B$16*10000 | D36: 万元/年
A38: ④ 关键判断
A39: 临界克重（与基准打平） | B39: =$B$17/(($D$26+$B$14)/1000000) | C39: gsm
A40: 实际克重超出临界 | B40: =$B$8-B39 | C40: gsm
A41: 成本结论 | B41: =IF(B33<=$B$17,"设计：优于传统","设计：高于传统")&" ｜ "&IF(C33<=$B$17,"实际：优于传统","实际：高于传统")
A42: 每降 1,000 元/t 纤维价 | B42: =$B$9*1000*$B$7/1000000 | C42: 元/m²
A45: 辅助：非 PTT 组分加权单价 元/t | B45: =(34*$B$10+8*$B$11+30*$B$12+6*$B$13)/78

Sheet Compare
A1: 28gsm 新 REL vs 40gsm 传统 REL · 方案对比
A2: 新 REL 数据实时引用 Model 页；传统基线为竞品实测配方（PET 短纤 9,100、PE/PP 9,300、Lyocell 22,000）
A4: 方案 | B4: 克重 gsm | C4: 配方 元/t | D4: 纤维 元/m² | E4: 加工 元/m² | F4: 全成本 元/m² | G4: 元/片 | H4: vs 传统均值
A5: 新 REL · 设计克重 | B5: =Model!$B$7 | C5: =Model!$D$26 | D5: =C5*B5/1000000 | E5: =Model!$B$14*B5/1000000 | F5: =D5+E5 | G5: =F5*Model!$B$15 | H5: =F5/$F$11-1
A6: 新 REL · 实际成网 | B6: =Model!$B$8 | C6: =Model!$D$26 | D6: =C6*B6/1000000 | E6: =Model!$B$14*B6/1000000 | F6: =D6+E6 | G6: =F6*Model!$B$15 | H6: =F6/$F$11-1
A7: B1 · YJ DL24C | B7: 39.8 | C7: 10600 | D7: =C7*B7/1000000 | E7: =Model!$B$14*B7/1000000 | F7: =D7+E7 | G7: =F7*Model!$B$15 | H7: =F7/$F$11-1
A8: B2 · DY ND055 | B8: 38.8 | C8: 10350 | D8: =C8*B8/1000000 | E8: =Model!$B$14*B8/1000000 | F8: =D8+E8 | G8: =F8*Model!$B$15 | H8: =F8/$F$11-1
A9: B3 · ZB 箱式 | B9: 40 | C9: 10146 | D9: =C9*B9/1000000 | E9: =Model!$B$14*B9/1000000 | F9: =D9+E9 | G9: =F9*Model!$B$15 | H9: =F9/$F$11-1
A10: B4 · 藤东 | B10: 40 | C10: 9170 | D10: =C10*B10/1000000 | E10: =Model!$B$14*B10/1000000 | F10: =D10+E10 | G10: =F10*Model!$B$15 | H10: =F10/$F$11-1
A11: 传统基线均值 | B11: =AVERAGE(B7:B10) | D11: =AVERAGE(D7:D10) | E11: =AVERAGE(E7:E10) | F11: =AVERAGE(F7:F10) | G11: =AVERAGE(G7:G10)
A13: 读数：设计克重下 28.8gsm 优于传统均值；一旦回缩到 33gsm，克重优势被配方溢价吃掉，成本反超。临界克重见 Model!B39。

Sheet Sensitivity
A1: 敏感度矩阵 · 全成本 元/m²
A2: 绿色=低于 40gsm 传统均值 ｜ 红色=高于 ｜ 由 Model 页参数驱动
A4: 表 1 ｜ 纤维价（横）× 克重（纵）
A5: 克重 \ 纤维价 | B5: 19000 | C5: 19500 | D5: 20000 | E5: 20500 | F5: 21000 | G5: 21500 | H5: 22000
A6: 28 | B6: =(Model!$B$45*(1-Model!$B$9)+Model!$B$9*B$5+Model!$B$14)*$A6/1000000 | C6: =(Model!$B$45*(1-Model!$B$9)+Model!$B$9*C$5+Model!$B$14)*$A6/1000000 | D6: =(Model!$B$45*(1-Model!$B$9)+Model!$B$9*D$5+Model!$B$14)*$A6/1000000 | E6: =(Model!$B$45*(1-Model!$B$9)+Model!$B$9*E$5+Model!$B$14)*$A6/1000000 | F6: =(Model!$B$45*(1-Model!$B$9)+Model!$B$9*F$5+Model!$B$14)*$A6/1000000 | G6: =(Model!$B$45*(1-Model!$B$9)+Model!$B$9*G$5+Model!$B$14)*$A6/1000000 | H6: =(Model!$B$45*(1-Model!$B$9)+Model!$B$9*H$5+Model!$B$14)*$A6/1000000
A7: 29 | B7: =(Model!$B$45*(1-Model!$B$9)+Model!$B$9*B$5+Model!$B$14)*$A7/1000000 | C7: =(Model!$B$45*(1-Model!$B$9)+Model!$B$9*C$5+Model!$B$14)*$A7/1000000 | D7: =(Model!$B$45*(1-Model!$B$9)+Model!$B$9*D$5+Model!$B$14)*$A7/1000000 | E7: =(Model!$B$45*(1-Model!$B$9)+Model!$B$9*E$5+Model!$B$14)*$A7/1000000 | F7: =(Model!$B$45*(1-Model!$B$9)+Model!$B$9*F$5+Model!$B$14)*$A7/1000000 | G7: =(Model!$B$45*(1-Model!$B$9)+Model!$B$9*G$5+Model!$B$14)*$A7/1000000 | H7: =(Model!$B$45*(1-Model!$B$9)+Model!$B$9*H$5+Model!$B$14)*$A7/1000000
A8: 30 | B8: =(Model!$B$45*(1-Model!$B$9)+Model!$B$9*B$5+Model!$B$14)*$A8/1000000 | C8: =(Model!$B$45*(1-Model!$B$9)+Model!$B$9*C$5+Model!$B$14)*$A8/1000000 | D8: =(Model!$B$45*(1-Model!$B$9)+Model!$B$9*D$5+Model!$B$14)*$A8/1000000 | E8: =(Model!$B$45*(1-Model!$B$9)+Model!$B$9*E$5+Model!$B$14)*$A8/1000000 | F8: =(Model!$B$45*(1-Model!$B$9)+Model!$B$9*F$5+Model!$B$14)*$A8/1000000 | G8: =(Model!$B$45*(1-Model!$B$9)+Model!$B$9*G$5+Model!$B$14)*$A8/1000000 | H8: =(Model!$B$45*(1-Model!$B$9)+Model!$B$9*H$5+Model!$B$14)*$A8/1000000
A9: 31 | B9: =(Model!$B$45*(1-Model!$B$9)+Model!$B$9*B$5+Model!$B$14)*$A9/1000000 | C9: =(Model!$B$45*(1-Model!$B$9)+Model!$B$9*C$5+Model!$B$14)*$A9/1000000 | D9: =(Model!$B$45*(1-Model!$B$9)+Model!$B$9*D$5+Model!$B$14)*$A9/1000000 | E9: =(Model!$B$45*(1-Model!$B$9)+Model!$B$9*E$5+Model!$B$14)*$A9/1000000 | F9: =(Model!$B$45*(1-Model!$B$9)+Model!$B$9*F$5+Model!$B$14)*$A9/1000000 | G9: =(Model!$B$45*(1-Model!$B$9)+Model!$B$9*G$5+Model!$B$14)*$A9/1000000 | H9: =(Model!$B$45*(1-Model!$B$9)+Model!$B$9*H$5+Model!$B$14)*$A9/1000000
A10: 32 | B10: =(Model!$B$45*(1-Model!$B$9)+Model!$B$9*B$5+Model!$B$14)*$A10/1000000 | C10: =(Model!$B$45*(1-Model!$B$9)+Model!$B$9*C$5+Model!$B$14)*$A10/1000000 | D10: =(Model!$B$45*(1-Model!$B$9)+Model!$B$9*D$5+Model!$B$14)*$A10/1000000 | E10: =(Model!$B$45*(1-Model!$B$9)+Model!$B$9*E$5+Model!$B$14)*$A10/1000000 | F10: =(Model!$B$45*(1-Model!$B$9)+Model!$B$9*F$5+Model!$B$14)*$A10/1000000 | G10: =(Model!$B$45*(1-Model!$B$9)+Model!$B$9*G$5+Model!$B$14)*$A10/1000000 | H10: =(Model!$B$45*(1-Model!$B$9)+Model!$B$9*H$5+Model!$B$14)*$A10/1000000
A11: 33 | B11: =(Model!$B$45*(1-Model!$B$9)+Model!$B$9*B$5+Model!$B$14)*$A11/1000000 | C11: =(Model!$B$45*(1-Model!$B$9)+Model!$B$9*C$5+Model!$B$14)*$A11/1000000 | D11: =(Model!$B$45*(1-Model!$B$9)+Model!$B$9*D$5+Model!$B$14)*$A11/1000000 | E11: =(Model!$B$45*(1-Model!$B$9)+Model!$B$9*E$5+Model!$B$14)*$A11/1000000 | F11: =(Model!$B$45*(1-Model!$B$9)+Model!$B$9*F$5+Model!$B$14)*$A11/1000000 | G11: =(Model!$B$45*(1-Model!$B$9)+Model!$B$9*G$5+Model!$B$14)*$A11/1000000 | H11: =(Model!$B$45*(1-Model!$B$9)+Model!$B$9*H$5+Model!$B$14)*$A11/1000000
A12: 34 | B12: =(Model!$B$45*(1-Model!$B$9)+Model!$B$9*B$5+Model!$B$14)*$A12/1000000 | C12: =(Model!$B$45*(1-Model!$B$9)+Model!$B$9*C$5+Model!$B$14)*$A12/1000000 | D12: =(Model!$B$45*(1-Model!$B$9)+Model!$B$9*D$5+Model!$B$14)*$A12/1000000 | E12: =(Model!$B$45*(1-Model!$B$9)+Model!$B$9*E$5+Model!$B$14)*$A12/1000000 | F12: =(Model!$B$45*(1-Model!$B$9)+Model!$B$9*F$5+Model!$B$14)*$A12/1000000 | G12: =(Model!$B$45*(1-Model!$B$9)+Model!$B$9*G$5+Model!$B$14)*$A12/1000000 | H12: =(Model!$B$45*(1-Model!$B$9)+Model!$B$9*H$5+Model!$B$14)*$A12/1000000
A15: 表 2 ｜ PTT 比例（横）× 克重（纵）
A16: 克重 \ PTT% | B16: 0.1 | C16: 0.15 | D16: 0.18 | E16: 0.2 | F16: 0.22 | G16: 0.25 | H16: 0.3
A17: 28 | B17: =(Model!$B$45*(1-B$16)+B$16*Model!$B$6+Model!$B$14)*$A17/1000000 | C17: =(Model!$B$45*(1-C$16)+C$16*Model!$B$6+Model!$B$14)*$A17/1000000 | D17: =(Model!$B$45*(1-D$16)+D$16*Model!$B$6+Model!$B$14)*$A17/1000000 | E17: =(Model!$B$45*(1-E$16)+E$16*Model!$B$6+Model!$B$14)*$A17/1000000 | F17: =(Model!$B$45*(1-F$16)+F$16*Model!$B$6+Model!$B$14)*$A17/1000000 | G17: =(Model!$B$45*(1-G$16)+G$16*Model!$B$6+Model!$B$14)*$A17/1000000 | H17: =(Model!$B$45*(1-H$16)+H$16*Model!$B$6+Model!$B$14)*$A17/1000000
A18: 29 | B18: =(Model!$B$45*(1-B$16)+B$16*Model!$B$6+Model!$B$14)*$A18/1000000 | C18: =(Model!$B$45*(1-C$16)+C$16*Model!$B$6+Model!$B$14)*$A18/1000000 | D18: =(Model!$B$45*(1-D$16)+D$16*Model!$B$6+Model!$B$14)*$A18/1000000 | E18: =(Model!$B$45*(1-E$16)+E$16*Model!$B$6+Model!$B$14)*$A18/1000000 | F18: =(Model!$B$45*(1-F$16)+F$16*Model!$B$6+Model!$B$14)*$A18/1000000 | G18: =(Model!$B$45*(1-G$16)+G$16*Model!$B$6+Model!$B$14)*$A18/1000000 | H18: =(Model!$B$45*(1-H$16)+H$16*Model!$B$6+Model!$B$14)*$A18/1000000
A19: 30 | B19: =(Model!$B$45*(1-B$16)+B$16*Model!$B$6+Model!$B$14)*$A19/1000000 | C19: =(Model!$B$45*(1-C$16)+C$16*Model!$B$6+Model!$B$14)*$A19/1000000 | D19: =(Model!$B$45*(1-D$16)+D$16*Model!$B$6+Model!$B$14)*$A19/1000000 | E19: =(Model!$B$45*(1-E$16)+E$16*Model!$B$6+Model!$B$14)*$A19/1000000 | F19: =(Model!$B$45*(1-F$16)+F$16*Model!$B$6+Model!$B$14)*$A19/1000000 | G19: =(Model!$B$45*(1-G$16)+G$16*Model!$B$6+Model!$B$14)*$A19/1000000 | H19: =(Model!$B$45*(1-H$16)+H$16*Model!$B$6+Model!$B$14)*$A19/1000000
A20: 31 | B20: =(Model!$B$45*(1-B$16)+B$16*Model!$B$6+Model!$B$14)*$A20/1000000 | C20: =(Model!$B$45*(1-C$16)+C$16*Model!$B$6+Model!$B$14)*$A20/1000000 | D20: =(Model!$B$45*(1-D$16)+D$16*Model!$B$6+Model!$B$14)*$A20/1000000 | E20: =(Model!$B$45*(1-E$16)+E$16*Model!$B$6+Model!$B$14)*$A20/1000000 | F20: =(Model!$B$45*(1-F$16)+F$16*Model!$B$6+Model!$B$14)*$A20/1000000 | G20: =(Model!$B$45*(1-G$16)+G$16*Model!$B$6+Model!$B$14)*$A20/1000000 | H20: =(Model!$B$45*(1-H$16)+H$16*Model!$B$6+Model!$B$14)*$A20/1000000
A21: 32 | B21: =(Model!$B$45*(1-B$16)+B$16*Model!$B$6+Model!$B$14)*$A21/1000000 | C21: =(Model!$B$45*(1-C$16)+C$16*Model!$B$6+Model!$B$14)*$A21/1000000 | D21: =(Model!$B$45*(1-D$16)+D$16*Model!$B$6+Model!$B$14)*$A21/1000000 | E21: =(Model!$B$45*(1-E$16)+E$16*Model!$B$6+Model!$B$14)*$A21/1000000 | F21: =(Model!$B$45*(1-F$16)+F$16*Model!$B$6+Model!$B$14)*$A21/1000000 | G21: =(Model!$B$45*(1-G$16)+G$16*Model!$B$6+Model!$B$14)*$A21/1000000 | H21: =(Model!$B$45*(1-H$16)+H$16*Model!$B$6+Model!$B$14)*$A21/1000000
A22: 33 | B22: =(Model!$B$45*(1-B$16)+B$16*Model!$B$6+Model!$B$14)*$A22/1000000 | C22: =(Model!$B$45*(1-C$16)+C$16*Model!$B$6+Model!$B$14)*$A22/1000000 | D22: =(Model!$B$45*(1-D$16)+D$16*Model!$B$6+Model!$B$14)*$A22/1000000 | E22: =(Model!$B$45*(1-E$16)+E$16*Model!$B$6+Model!$B$14)*$A22/1000000 | F22: =(Model!$B$45*(1-F$16)+F$16*Model!$B$6+Model!$B$14)*$A22/1000000 | G22: =(Model!$B$45*(1-G$16)+G$16*Model!$B$6+Model!$B$14)*$A22/1000000 | H22: =(Model!$B$45*(1-H$16)+H$16*Model!$B$6+Model!$B$14)*$A22/1000000
A23: 34 | B23: =(Model!$B$45*(1-B$16)+B$16*Model!$B$6+Model!$B$14)*$A23/1000000 | C23: =(Model!$B$45*(1-C$16)+C$16*Model!$B$6+Model!$B$14)*$A23/1000000 | D23: =(Model!$B$45*(1-D$16)+D$16*Model!$B$6+Model!$B$14)*$A23/1000000 | E23: =(Model!$B$45*(1-E$16)+E$16*Model!$B$6+Model!$B$14)*$A23/1000000 | F23: =(Model!$B$45*(1-F$16)+F$16*Model!$B$6+Model!$B$14)*$A23/1000000 | G23: =(Model!$B$45*(1-G$16)+G$16*Model!$B$6+Model!$B$14)*$A23/1000000 | H23: =(Model!$B$45*(1-H$16)+H$16*Model!$B$6+Model!$B$14)*$A23/1000000
A26: 表 3 ｜ 相对传统均值年度金额差（万元/年，正=多花，按 1 亿片/年）
A27: 克重 \ 纤维价 | B27: 19000 | C27: 19500 | D27: 20000 | E27: 20500 | F27: 21000 | G27: 21500 | H27: 22000
A28: 28 | B28: =(((Model!$B$45*(1-Model!$B$9)+Model!$B$9*B$27+Model!$B$14)*$A28/1000000)-Model!$B$17)*Model!$B$15*Model!$B$16*10000 | C28: =(((Model!$B$45*(1-Model!$B$9)+Model!$B$9*C$27+Model!$B$14)*$A28/1000000)-Model!$B$17)*Model!$B$15*Model!$B$16*10000 | D28: =(((Model!$B$45*(1-Model!$B$9)+Model!$B$9*D$27+Model!$B$14)*$A28/1000000)-Model!$B$17)*Model!$B$15*Model!$B$16*10000 | E28: =(((Model!$B$45*(1-Model!$B$9)+Model!$B$9*E$27+Model!$B$14)*$A28/1000000)-Model!$B$17)*Model!$B$15*Model!$B$16*10000 | F28: =(((Model!$B$45*(1-Model!$B$9)+Model!$B$9*F$27+Model!$B$14)*$A28/1000000)-Model!$B$17)*Model!$B$15*Model!$B$16*10000 | G28: =(((Model!$B$45*(1-Model!$B$9)+Model!$B$9*G$27+Model!$B$14)*$A28/1000000)-Model!$B$17)*Model!$B$15*Model!$B$16*10000 | H28: =(((Model!$B$45*(1-Model!$B$9)+Model!$B$9*H$27+Model!$B$14)*$A28/1000000)-Model!$B$17)*Model!$B$15*Model!$B$16*10000
A29: 29 | B29: =(((Model!$B$45*(1-Model!$B$9)+Model!$B$9*B$27+Model!$B$14)*$A29/1000000)-Model!$B$17)*Model!$B$15*Model!$B$16*10000 | C29: =(((Model!$B$45*(1-Model!$B$9)+Model!$B$9*C$27+Model!$B$14)*$A29/1000000)-Model!$B$17)*Model!$B$15*Model!$B$16*10000 | D29: =(((Model!$B$45*(1-Model!$B$9)+Model!$B$9*D$27+Model!$B$14)*$A29/1000000)-Model!$B$17)*Model!$B$15*Model!$B$16*10000 | E29: =(((Model!$B$45*(1-Model!$B$9)+Model!$B$9*E$27+Model!$B$14)*$A29/1000000)-Model!$B$17)*Model!$B$15*Model!$B$16*10000 | F29: =(((Model!$B$45*(1-Model!$B$9)+Model!$B$9*F$27+Model!$B$14)*$A29/1000000)-Model!$B$17)*Model!$B$15*Model!$B$16*10000 | G29: =(((Model!$B$45*(1-Model!$B$9)+Model!$B$9*G$27+Model!$B$14)*$A29/1000000)-Model!$B$17)*Model!$B$15*Model!$B$16*10000 | H29: =(((Model!$B$45*(1-Model!$B$9)+Model!$B$9*H$27+Model!$B$14)*$A29/1000000)-Model!$B$17)*Model!$B$15*Model!$B$16*10000
A30: 30 | B30: =(((Model!$B$45*(1-Model!$B$9)+Model!$B$9*B$27+Model!$B$14)*$A30/1000000)-Model!$B$17)*Model!$B$15*Model!$B$16*10000 | C30: =(((Model!$B$45*(1-Model!$B$9)+Model!$B$9*C$27+Model!$B$14)*$A30/1000000)-Model!$B$17)*Model!$B$15*Model!$B$16*10000 | D30: =(((Model!$B$45*(1-Model!$B$9)+Model!$B$9*D$27+Model!$B$14)*$A30/1000000)-Model!$B$17)*Model!$B$15*Model!$B$16*10000 | E30: =(((Model!$B$45*(1-Model!$B$9)+Model!$B$9*E$27+Model!$B$14)*$A30/1000000)-Model!$B$17)*Model!$B$15*Model!$B$16*10000 | F30: =(((Model!$B$45*(1-Model!$B$9)+Model!$B$9*F$27+Model!$B$14)*$A30/1000000)-Model!$B$17)*Model!$B$15*Model!$B$16*10000 | G30: =(((Model!$B$45*(1-Model!$B$9)+Model!$B$9*G$27+Model!$B$14)*$A30/1000000)-Model!$B$17)*Model!$B$15*Model!$B$16*10000 | H30: =(((Model!$B$45*(1-Model!$B$9)+Model!$B$9*H$27+Model!$B$14)*$A30/1000000)-Model!$B$17)*Model!$B$15*Model!$B$16*10000
A31: 31 | B31: =(((Model!$B$45*(1-Model!$B$9)+Model!$B$9*B$27+Model!$B$14)*$A31/1000000)-Model!$B$17)*Model!$B$15*Model!$B$16*10000 | C31: =(((Model!$B$45*(1-Model!$B$9)+Model!$B$9*C$27+Model!$B$14)*$A31/1000000)-Model!$B$17)*Model!$B$15*Model!$B$16*10000 | D31: =(((Model!$B$45*(1-Model!$B$9)+Model!$B$9*D$27+Model!$B$14)*$A31/1000000)-Model!$B$17)*Model!$B$15*Model!$B$16*10000 | E31: =(((Model!$B$45*(1-Model!$B$9)+Model!$B$9*E$27+Model!$B$14)*$A31/1000000)-Model!$B$17)*Model!$B$15*Model!$B$16*10000 | F31: =(((Model!$B$45*(1-Model!$B$9)+Model!$B$9*F$27+Model!$B$14)*$A31/1000000)-Model!$B$17)*Model!$B$15*Model!$B$16*10000 | G31: =(((Model!$B$45*(1-Model!$B$9)+Model!$B$9*G$27+Model!$B$14)*$A31/1000000)-Model!$B$17)*Model!$B$15*Model!$B$16*10000 | H31: =(((Model!$B$45*(1-Model!$B$9)+Model!$B$9*H$27+Model!$B$14)*$A31/1000000)-Model!$B$17)*Model!$B$15*Model!$B$16*10000
A32: 32 | B32: =(((Model!$B$45*(1-Model!$B$9)+Model!$B$9*B$27+Model!$B$14)*$A32/1000000)-Model!$B$17)*Model!$B$15*Model!$B$16*10000 | C32: =(((Model!$B$45*(1-Model!$B$9)+Model!$B$9*C$27+Model!$B$14)*$A32/1000000)-Model!$B$17)*Model!$B$15*Model!$B$16*10000 | D32: =(((Model!$B$45*(1-Model!$B$9)+Model!$B$9*D$27+Model!$B$14)*$A32/1000000)-Model!$B$17)*Model!$B$15*Model!$B$16*10000 | E32: =(((Model!$B$45*(1-Model!$B$9)+Model!$B$9*E$27+Model!$B$14)*$A32/1000000)-Model!$B$17)*Model!$B$15*Model!$B$16*10000 | F32: =(((Model!$B$45*(1-Model!$B$9)+Model!$B$9*F$27+Model!$B$14)*$A32/1000000)-Model!$B$17)*Model!$B$15*Model!$B$16*10000 | G32: =(((Model!$B$45*(1-Model!$B$9)+Model!$B$9*G$27+Model!$B$14)*$A32/1000000)-Model!$B$17)*Model!$B$15*Model!$B$16*10000 | H32: =(((Model!$B$45*(1-Model!$B$9)+Model!$B$9*H$27+Model!$B$14)*$A32/1000000)-Model!$B$17)*Model!$B$15*Model!$B$16*10000
A33: 33 | B33: =(((Model!$B$45*(1-Model!$B$9)+Model!$B$9*B$27+Model!$B$14)*$A33/1000000)-Model!$B$17)*Model!$B$15*Model!$B$16*10000 | C33: =(((Model!$B$45*(1-Model!$B$9)+Model!$B$9*C$27+Model!$B$14)*$A33/1000000)-Model!$B$17)*Model!$B$15*Model!$B$16*10000 | D33: =(((Model!$B$45*(1-Model!$B$9)+Model!$B$9*D$27+Model!$B$14)*$A33/1000000)-Model!$B$17)*Model!$B$15*Model!$B$16*10000 | E33: =(((Model!$B$45*(1-Model!$B$9)+Model!$B$9*E$27+Model!$B$14)*$A33/1000000)-Model!$B$17)*Model!$B$15*Model!$B$16*10000 | F33: =(((Model!$B$45*(1-Model!$B$9)+Model!$B$9*F$27+Model!$B$14)*$A33/1000000)-Model!$B$17)*Model!$B$15*Model!$B$16*10000 | G33: =(((Model!$B$45*(1-Model!$B$9)+Model!$B$9*G$27+Model!$B$14)*$A33/1000000)-Model!$B$17)*Model!$B$15*Model!$B$16*10000 | H33: =(((Model!$B$45*(1-Model!$B$9)+Model!$B$9*H$27+Model!$B$14)*$A33/1000000)-Model!$B$17)*Model!$B$15*Model!$B$16*10000
A34: 34 | B34: =(((Model!$B$45*(1-Model!$B$9)+Model!$B$9*B$27+Model!$B$14)*$A34/1000000)-Model!$B$17)*Model!$B$15*Model!$B$16*10000 | C34: =(((Model!$B$45*(1-Model!$B$9)+Model!$B$9*C$27+Model!$B$14)*$A34/1000000)-Model!$B$17)*Model!$B$15*Model!$B$16*10000 | D34: =(((Model!$B$45*(1-Model!$B$9)+Model!$B$9*D$27+Model!$B$14)*$A34/1000000)-Model!$B$17)*Model!$B$15*Model!$B$16*10000 | E34: =(((Model!$B$45*(1-Model!$B$9)+Model!$B$9*E$27+Model!$B$14)*$A34/1000000)-Model!$B$17)*Model!$B$15*Model!$B$16*10000 | F34: =(((Model!$B$45*(1-Model!$B$9)+Model!$B$9*F$27+Model!$B$14)*$A34/1000000)-Model!$B$17)*Model!$B$15*Model!$B$16*10000 | G34: =(((Model!$B$45*(1-Model!$B$9)+Model!$B$9*G$27+Model!$B$14)*$A34/1000000)-Model!$B$17)*Model!$B$15*Model!$B$16*10000 | H34: =(((Model!$B$45*(1-Model!$B$9)+Model!$B$9*H$27+Model!$B$14)*$A34/1000000)-Model!$B$17)*Model!$B$15*Model!$B$16*10000

Sheet Assumptions
A1: 价格假设与口径说明
A2: 所有价格为含税到厂口径；标注【待核】项在定稿前需供应商书面确认
A4: 项目 | B4: 数值 | C4: 单位 | D4: 来源 / 说明
A5: PTT/PET S/S 纤维 | B5: 20500 | C5: 元/t | D5: 恒碳千吨级交底 20,000–21,000；26,000 系小样价不适用
A6: └ 价格拆解 | B6: — | C6: — | D6: PTT 18,000×50% + PET 8,600×50% + 纺丝 4,000 + 成品率 94–95% + 运输 400 + 溢价 1,500–2,500
A7: PTT 切片（1,500t 口径） | B7: 18000 | C7: 元/t | D7: 会议口径；油价回落至 5,500 时可至 17,000
A8: PTA | B8: 6800 | C8: 元/t | D8: 会议口径，高油价时期价格
A9: PET 纤维级半光切片 | B9: 8600 | C9: 元/t | D9: 10/15 华东主流商谈 8,500–8,800，自提
A10: PET 单组分短纤 | B10: 9100 | C10: 元/t | D10: 10/16 直纺基准 8,930；10/19 品牌 9,250–9,400
A11: ES CoPET/PET 2D/3D | B11: 11600 | C11: 元/t | D11: 卫材级复合短纤，江南高纤均价折算
A12: 偏心中空 ES | B12: 13500 | C12: 元/t | D12: 【待核】原生中空 7D 10,100–10,200 + ES 皮芯溢价
A13: PVA 水不溶 6D | B13: 20000 | C13: 元/t | D13: 皖维高新报价
A14: 加工费（ATB） | B14: 4500 | C14: 元/t | D14: 热风粘合 + 分切，含能耗与人工
A15: 复合纺丝费（双组份） | B15: 4000 | C15: 元/t | D15: 会议口径「4,000 多元」，普通短纤仅 900–1,000
A16: 成品率 | B16: 94–95% | C16: — | D16: 会议口径
A17: 单片面积 | B17: 0.038 | C17: m² | D17: 约 100×380mm，按实际规格调整
A18: 年产量 | B18: 1 | C18: 亿片 | D18: 用于年度金额换算
A19: 设计克重 | B19: 28.8 | C19: gsm | D19: Code A 实测；标称 28gsm
A20: 实际成网克重 | B20: 33 | C20: gsm | D20: 会议：布 28–29gsm 到工厂回缩至 33gsm
A21: PTT 添加比例 | B21: 22% | C21: % | D21: 会议确认，10–30% 合理；超 30% 骨感差
A22: 传统 40gsm 均值 | B22: 0.5775 | C22: 元/m² | D22: YJ/DY/ZB/藤东 四基线，PET 短纤按 9,100 计
A24: 未含项：3–5% 工艺损耗、分切废料、打样摊销、关税与认证（ISCC 等）单独费用。
